iclockhelper/__init__.py
iclockhelper/models.py
iclockhelper/requests.py
iclockhelper-0.0.4.dist-info/AUTHORS.rst
iclockhelper-0.0.4.dist-info/LICENSE.txt
iclockhelper-0.0.4.dist-info/METADATA
iclockhelper-0.0.4.dist-info/WHEEL
iclockhelper-0.0.4.dist-info/top_level.txt
iclockhelper-0.0.4.dist-info/RECORD
