Metadata-Version: 2.1
Name: iclockhelper
Version: 0.0.4
Summary: Helper library to parse income request from IClock ADMS(like ZKTeco)
Home-page: https://github.com/fedotovaleksandr/iclockhelper
Author: afedotov
Author-email: mr.fedotovaleksandr@gmail.com
License: mit
Project-URL: Documentation, https://github.com/fedotovaleksandr/iclockhelper
Platform: any
Classifier: Development Status :: 4 - Beta
Classifier: Programming Language :: Python
Requires-Python: >=3.7
Requires-Dist: stringcase
Requires-Dist: pytz
Provides-Extra: testing
Requires-Dist: pytest ; extra == 'testing'
Requires-Dist: pytest-cov ; extra == 'testing'
